funmd/__init__.py
funmd/_pandas.py
funmd-0.1.2.dist-info/LICENSE
funmd-0.1.2.dist-info/METADATA
funmd-0.1.2.dist-info/WHEEL
funmd-0.1.2.dist-info/top_level.txt
funmd-0.1.2.dist-info/RECORD
