Metadata-Version: 2.1
Name: funmd
Version: 0.1.2
Summary: Add your description here
Requires-Python: >=3.8
License-File: LICENSE
Requires-Dist: funutil>=1.0.32
